part_2/verilog/mac.v
// Created by prof. Mingu Kang @VVIP Lab in UCSD ECE department
// Please do not spread this code without permission 
module mac (out, a, b0, b1, c, simd);

parameter bw = 4;
parameter psum_bw = 18; // This needs to be 18 for 2b lane reconfig 

localparam aw = bw/2;
localparam simd_bw = psum_bw/2;

output signed [psum_bw-1:0] out;
input signed  [bw-1:0] a;  // activation
input signed  [bw-1:0] b0;  // weight
input signed  [bw-1:0] b1;  // weight
input signed  [psum_bw-1:0] c;
input simd; //simd = 1 is 2 bit lane

// keeping product width simd_bw for now. Can also do 2*bw
wire signed [aw+bw-1:0] product0, product1;
wire signed [aw:0]   a_pad0, a_pad1;
wire signed [psum_bw-1:0] psum, simd_psum;
wire signed [psum_bw-1:0] product; // 
wire signed [2*bw-1:0] shifted_product1; // shifted_product1 left shifts upper product
wire signed [simd_bw-1:0] psum0, psum1;
wire signed [simd_bw-1:0] c0, c1;

assign a_pad0 = {1'b0, a[aw-1:0]}; //force unsigned lower activation
assign a_pad1 = {1'b0, a[2*aw-1:aw]}; //force unsigned upper activation 


assign product0 = a_pad0 * b0;
assign product1 = a_pad1 * b1;

// Simd output calculations
// Upper and lower c, only needed for simd
assign c0 = c[simd_bw-1:0];
assign c1 = c[2*simd_bw-1:simd_bw];

assign psum0 = product0 + c0;
assign psum1 = product1 + c1;
assign simd_psum = {psum1, psum0};

//Regular output calculations from shifted partial products 
assign shifted_product1 = {product1, {aw{1'b0}}};
assign product = shifted_product1 + product0; // product0 should be inferred as signed
assign psum = product + c;

// Assign output based on simd selector
assign out = simd? simd_psum : psum;

endmodule

part_2/verilog/mac_tb.v
`timescale 1ns/1ps

module mac_tb;

  // Parameters must match DUT
  localparam bw       = 4;
  localparam aw = 2;
  localparam psum_bw  = 18;
  localparam simd_bw = 9;

  // DUT signals
  reg  signed  [bw-1:0]     a;
  reg  signed  [bw-1:0]     b0, b1;
  reg  signed  [psum_bw-1:0] c;
  reg                       simd;
  wire signed [psum_bw-1:0] out;

  // DUT instance
  mac dut (
    .out(out),
    .a(a),
    .b0(b0),
    .b1(b1),
    .c(c),
    .simd(simd)
  );

  // Task for one test
  task run_test;
    input signed [bw-1:0]      a_in;
    input signed [bw-1:0]      b_in;
    input signed [simd_bw-1:0] c_in;
    reg   signed [simd_bw-1:0] expected;
    reg signed [bw:0] a_pad;
    begin
      a   = a_in;
      b0  = b_in;
      b1  = b_in;   // must match in non-SIMD mode
      c   = c_in;
      simd = 0;

      #1; // allow settle

      a_pad = {1'b0, a_in};
      expected = a_pad * b_in + c_in;

      $display("a=%0d  b=%0d  c=%0d  out=%0d  expected=%0d %s",
                $unsigned(a_in),    b_in,    c_in,     out,      expected,
                (out === expected) ? "PASS" : "FAIL");
    end
  endtask

  // Task for one test
  task run_simd;
    input  signed [aw-1:0]      a0_in;
    input  signed [aw-1:0]      a1_in;
    input signed [bw-1:0]      b0_in;
    input signed [bw-1:0]      b1_in;
    input signed [psum_bw-1:0] c0_in;
    input signed [simd_bw-1:0] c1_in;
    reg   signed [simd_bw-1:0] expected0, expected1;
    reg signed [bw:0] a0_pad, a1_pad;
    begin
      a[1:0]   = a0_in;
      a[3:2]   = a1_in;
      b0  = b0_in;
      b1  = b1_in;   // must match in non-SIMD mode
      c[simd_bw-1:0]   = c0_in;
      c[2*simd_bw-1:simd_bw]   = c1_in;
      simd = 1;

      #1; // allow settle

      a0_pad = {1'b0, a0_in};
      a1_pad = {1'b0, a1_in};

      expected0 = a0_pad * b0_in + c0_in;
      expected1 = a1_pad * b1_in + c1_in;

      $display("a0=%0d a1=%0d b0=%0d b1=%0d c0=%0d c1=%0d |  psum0=%0d psum1=%0d | expected0=%0d expected1=%0d %s",
                $unsigned(a0_in), $unsigned(a1_in), b0_in, b1_in, c0_in, c1_in,
                $signed(out[simd_bw-1:0]), $signed(out[2*simd_bw-1:simd_bw]),
                expected0, expected1,
                ((out[simd_bw-1:0] === expected0) && (out[2*simd_bw-1:simd_bw] === expected1)) ? "PASS" : "FAIL");
    end
  endtask

  initial begin
    $display("=== NON-SIMD MODE TESTS ===");

    $dumpfile("mac_tb.vcd");
    $dumpvars(0,mac_tb);

    run_test(4'd3, 4'sd2, 18'sd5);     // 3*2 + 5 = 11
    run_test(4'd5, -4'sd3, 18'sd0);   // 5*(-3)  = -15
    run_test(4'd2, -4'sd1, 18'sd10);   // 2*(-1) + 10 = 8
    run_test(4'd15, 4'sd7, 18'sd0);    // max a, pos b 105
    run_test(4'd15, -4'sd8, 18'sd0);    // max a neg b -120
    run_test(4'd15, 4'sd7, 18'sd300);    // max a, pos b 405
    run_test(4'd15, -4'sd8, -18'sd300);    // max a neg b -420

    $display("********************************");
    $display("");
    $display("=== NON-SIMD MODE TESTS ===");

    run_simd(2'd0, 2'd1, 4'sd2, -4'sd1, 9'sd5, 9'sd10);  //0*2+5 = 5, 1*-1+10 = 9
    run_simd(2'd1, 2'd2, 4'sd3, 4'sd1, 9'sd0, 9'sd7); //1*3+0=3, 2*1+7=9
    run_simd(2'd2, 2'd3, -4'sd8, 4'sd7, 9'sd3, 9'sd4); // 2*-8+3 = -13, 3*7+4=25
    run_simd(2'd3, 2'd3, 4'sd7, -4'sd8, 9'sd2, -9'sd100); // 3*7+2 = 23, 3*-8-300=

    // random stress
    // repeat (10) begin
    //   run_test($urandom_range(0,15),
    //            $urandom_range(-8,7),
    //            $urandom_range(-100,100));
    // end

    $finish;
  end

endmodule

part_2/mac_tb.vcd
$date
	Tue Nov 25 01:27:56 2025
$end
$version
	Icarus Verilog
$end
$timescale
	1ps
$end
$scope module mac_tb $end
$var wire 18 ! out [17:0] $end
$var reg 4 " a [3:0] $end
$var reg 4 # b0 [3:0] $end
$var reg 4 $ b1 [3:0] $end
$var reg 18 % c [17:0] $end
$var reg 1 & simd $end
$scope module dut $end
$var wire 4 ' a [3:0] $end
$var wire 4 ( b0 [3:0] $end
$var wire 4 ) b1 [3:0] $end
$var wire 18 * c [17:0] $end
$var wire 1 & simd $end
$var wire 18 + simd_psum [17:0] $end
$var wire 8 , shifted_product1 [7:0] $end
$var wire 9 - psum1 [8:0] $end
$var wire 9 . psum0 [8:0] $end
$var wire 18 / psum [17:0] $end
$var wire 6 0 product1 [5:0] $end
$var wire 6 1 product0 [5:0] $end
$var wire 18 2 product [17:0] $end
$var wire 18 3 out [17:0] $end
$var wire 9 4 c1 [8:0] $end
$var wire 9 5 c0 [8:0] $end
$var wire 3 6 a_pad1 [2:0] $end
$var wire 3 7 a_pad0 [2:0] $end
$upscope $end
$scope task run_simd $end
$var reg 2 8 a0_in [1:0] $end
$var reg 5 9 a0_pad [4:0] $end
$var reg 2 : a1_in [1:0] $end
$var reg 5 ; a1_pad [4:0] $end
$var reg 4 < b0_in [3:0] $end
$var reg 4 = b1_in [3:0] $end
$var reg 18 > c0_in [17:0] $end
$var reg 9 ? c1_in [8:0] $end
$var reg 9 @ expected0 [8:0] $end
$var reg 9 A expected1 [8:0] $end
$upscope $end
$scope task run_test $end
$var reg 4 B a_in [3:0] $end
$var reg 5 C a_pad [4:0] $end
$var reg 4 D b_in [3:0] $end
$var reg 9 E c_in [8:0] $end
$var reg 9 F expected [8:0] $end
$upscope $end
$upscope $end
$enddefinitions $end
#0
$dumpvars
bx F
b101 E
b10 D
bx C
b11 B
bx A
bx @
bx ?
bx >
bx =
bx <
bx ;
bx :
bx 9
bx 8
b11 7
b0 6
b101 5
b0 4
b1011 3
b110 2
b110 1
b0 0
b1011 /
b1011 .
b0 -
b0 ,
b1011 +
b101 *
b10 )
b10 (
b11 '
0&
b101 %
b10 $
b10 #
b11 "
b1011 !
$end
#1000
b0 5
b111111111111110001 !
b111111111111110001 3
b1 7
b111111101 -
b11110100 ,
b111101 0
b1 6
b0 %
b0 *
b1101 $
b1101 )
b111111101111111101 +
b111111101 .
b111111111111110001 /
b111111111111110001 2
b111101 1
b1101 #
b1101 (
b101 "
b101 '
b0 E
b1101 D
b101 B
b1011 F
b11 C
#2000
b1010 5
b1000 !
b1000 3
b10 7
b0 6
b1010 %
b1010 *
b0 -
b0 ,
b0 0
b1111 $
b1111 )
b1000 +
b1000 .
b1000 /
b111111111111111110 2
b111110 1
b1111 #
b1111 (
b10 "
b10 '
b1010 E
b1111 D
b10 B
b111110001 F
b101 C
#3000
b0 5
b1101001 !
b1101001 3
b11 7
b10101 -
b1010100 ,
b10101 0
b11 6
b0 %
b0 *
b111 $
b111 )
b10101000010101 +
b10101 .
b1101001 /
b1101001 2
b10101 1
b111 #
b111 (
b1111 "
b1111 '
b0 E
b111 D
b1111 B
b1000 F
b10 C
#4000
b111111111110001000 !
b111111111110001000 3
b111101000 -
b10100000 ,
b101000 0
b1000 $
b1000 )
b111101000111101000 +
b111101000 .
b111111111110001000 /
b111111111110001000 2
b101000 1
b1000 #
b1000 (
b1000 D
b1101001 F
b1111 C
#5000
b100101100 5
b111111111 4
b111111111110010101 !
b111111111110010101 3
b111111111100101100 %
b111111111100101100 *
b10100 -
b1010100 ,
b10101 0
b111 $
b111 )
b10100101000001 +
b101000001 .
b111111111110010101 /
b1101001 2
b10101 1
b111 #
b111 (
b100101100 E
b111 D
b110001000 F
#6000
b11010100 5
b0 4
b1011100 !
b1011100 3
b11010100 %
b11010100 *
b111101000 -
b10100000 ,
b101000 0
b1000 $
b1000 )
b111101000010111100 +
b10111100 .
b1011100 /
b111111111110001000 2
b101000 1
b1000 #
b1000 (
b11010100 E
b1000 D
b110010101 F
#7000
b1010 4
b101 5
b1001000000101 !
b1001000000101 3
b1 6
b0 7
1&
b1010000000101 %
b1010000000101 *
b1001 -
b11111100 ,
b111111 0
b1111 $
b1111 )
b1001000000101 +
b101 .
b1010000000001 /
b111111111111111100 2
b0 1
b10 #
b10 (
b100 "
b100 '
b1010 ?
b101 >
b1111 =
b10 <
b1 :
b0 8
b1011100 F
#8000
b111 4
b0 5
b1001000000011 !
b1001000000011 3
b10 6
b11 .
b11 1
b1 7
b111000000000 %
b111000000000 *
b1001000000011 +
b1001 -
b111000001011 /
b1011 2
b1000 ,
b10 0
b1 $
b1 )
b11 #
b11 (
b1001 "
b1001 '
b111 ?
b0 >
b1 =
b11 <
b10 :
b1 8
b1001 A
b101 @
b1 ;
b0 9
#9000
b100 4
b11 5
b11001111110011 !
b11001111110011 3
b11 6
b10 7
b100000000011 %
b100000000011 *
b11001 -
b1010100 ,
b10101 0
b111 $
b111 )
b11001111110011 +
b111110011 .
b100001000111 /
b1000100 2
b110000 1
b1000 #
b1000 (
b1110 "
b1110 '
b100 ?
b11 >
b111 =
b1000 <
b11 :
b10 8
b11 @
b10 ;
b1 9
#10000
b110011100 4
b10 5
b110000100000010111 !
b110000100000010111 3
b11 7
b110011100000000010 %
b110011100000000010 *
b110000100 -
b10100000 ,
b101000 0
b1000 $
b1000 )
b110000100000010111 +
b10111 .
b110011011110110111 /
b111111111110110101 2
b10101 1
b111 #
b111 (
b1111 "
b1111 '
b110011100 ?
b10 >
b1000 =
b111 <
b11 8
b11001 A
b111110011 @
b11 ;
b10 9
#11000
b110000100 A
b10111 @
b11 9
