part_2/verilog/mac.v
// Created by prof. Mingu Kang @VVIP Lab in UCSD ECE department
// Please do not spread this code without permission 
module mac (out, a, b0, b1, c, simd);

parameter bw = 4;
parameter psum_bw = 16; // This needs to be 16 for 2b lane reconfig 

localparam aw = bw/2;
localparam simd_bw = psum_bw/2;

output signed [psum_bw-1:0] out;
input signed  [bw-1:0] a;  // activation
input signed  [bw-1:0] b0;  // weight
input signed  [bw-1:0] b1;  // weight
input signed  [psum_bw-1:0] c;
input simd; //simd = 1 is 2 bit lane

// keeping product width simd_bw for now. Can also do 2*bw
wire signed [aw+bw-1:0] product0, product1;
wire signed [aw:0]   a_pad0, a_pad1;
wire signed [psum_bw-1:0] psum, simd_psum;
wire signed [psum_bw-1:0] product; // 
wire signed [2*bw-1:0] shifted_product1; // shifted_product1 left shifts upper product

assign a_pad0 = {1'b0, a[aw-1:0]}; //force unsigned lower activation
assign a_pad1 = {1'b0, a[2*aw-1:aw]}; //force unsigned upper activation 


assign product0 = a_pad0 * b0;
assign product1 = a_pad1 * b1;

// Simd output calculations
assign simd_psum = product1 + product0 + c;

//Regular output calculations from shifted partial products 
assign shifted_product1 = {product1, {aw{1'b0}}};
assign product = shifted_product1 + product0; // product0 should be inferred as signed
assign psum = product + c;

// Assign output based on simd selector
assign out = simd? simd_psum : psum;

endmodule

part_2/verilog/mac_tile.v
// Created by prof. Mingu Kang @VVIP Lab in UCSD ECE department
// Please do not spread this code without permission 
module mac_tile (clk, out_s, in_w, out_e, in_n, inst_w, inst_e, reset);

parameter bw = 4;
parameter psum_bw = 18;

output [psum_bw-1:0] out_s;
input  [bw-1:0] in_w; 
output [bw-1:0] out_e; 
input  [2:0] inst_w; // inst[2]: simd; inst[1]:execute, inst[0]: kernel loading
output [2:0] inst_e;
input  [psum_bw-1:0] in_n;
input  clk;
input  reset;

reg [bw-1:0] a_q;
reg [bw-1:0] b0_q, b1_q;
reg [psum_bw-1:0] c_q;
reg simd; // load while loading weight
wire [psum_bw-1:0] mac_out;

reg load_ready_q0, load_ready_q1;
reg [2:0] inst_q;

assign out_s = mac_out;
assign out_e = a_q;
assign inst_e = inst_q;

mac #(.bw(bw), .psum_bw(psum_bw)) mac_instance (
        .a(a_q), 
        .b0(b0_q),
        .b1(b1_q),
        .c(c_q),
        .simd(simd),
	.out(mac_out)
); 

always@ (posedge clk) begin
	if(reset) begin
		a_q <= 0;
		b0_q <= 0;
        b1_q <= 0;
		c_q <= 0;
		inst_q <= 0;
		load_ready_q0 <= 1'b1;
        load_ready_q1 <= 1'b1;
        simd <= 0;
	end
	else begin
		inst_q[1] <= inst_w[1];

		if(|inst_w[1:0]) begin
			a_q <= in_w;
			c_q <= in_n;
		end

		if(inst_w[0] && load_ready_q0 && !inst_w[2]) begin // not simd
			b0_q <= in_w;
            b1_q <= in_w;
            simd <= inst_w[2];
			load_ready_q0 <= 0;
            load_ready_q1 <= 0;
		end	

        if (inst_w[0] && load_ready_q0 && inst_w[2]) begin // simd load weight1
            b0_q <= in_w;
            simd <= inst_w[2];
            load_ready_q0 <= 0;
        end

        if (inst_w[0] && load_ready_q1 && !load_ready_q0 && simd) begin // simd load weight2 
            b1_q <= in_w;
            load_ready_q1 <= 0;
        end

		if (!load_ready_q0 && !load_ready_q1) begin
			inst_q[0] <= inst_w[0];
            inst_q[2] <= inst_w[2];
		end
	end
end

endmodule

part_3/verilog/mac_tile_tb.v
`timescale 1ns / 1ps

module mac_tile_tb;

  parameter bw = 4;
  parameter psum_bw = 16;

  reg clk, reset;
  reg [bw-1:0] in_w;
  reg [psum_bw-1:0] in_n;
  reg [2:0] inst_w;

  wire [psum_bw-1:0] out_s;
  wire [bw-1:0] out_e;
  wire [2:0] inst_e;

  // DUT
  // verilog_format: off
mac_tile #(.bw(bw), .psum_bw(psum_bw)) dut (
    .clk(clk), .reset(reset),
    .in_w(in_w),
    .out_e(out_e),
    .in_n(in_n),
    .inst_w(inst_w),
    .inst_e(inst_e),
    .out_s(out_s)
);
// verilog_format: on

  // ==== CLOCK ====
  always #5 clk = ~clk;

  // ==== TEST SEQUENCE ====
  initial begin

    $dumpfile("mac_tile_tb.vcd");
    $dumpvars(0, mac_tile_tb);

    clk = 0;
    reset = 1;
    in_w = 0;
    in_n = 0;
    inst_w = 0;

    // apply reset
    #20 reset = 0;
    inst_w[2] = 0;

    // -----------------------------------------
    // 1) FIRST LOAD (non-SIMD)
    // inst = 3'b001
    // Should load weight into b0 & b1, BUT nothing should appear at inst_e yet
    // -----------------------------------------
    $display("NON-SIMD mode");
    $display("\n--- LOAD WEIGHT #1 (non-SIMD) ---");
    in_w = 4'd3;
    inst_w[1:0] = 2'b01;  // non simd, ex=0, load weight = 1
    // #10 inst_w = 0;

    #10;
    // $display("inst_e = %b (expected 000)", inst_e);


    // -----------------------------------------
    // 2) SECOND LOAD (non-SIMD)
    // inst=001 again → now weights already loaded
    // Should push instruction to inst_e
    // out_e should forward previous in_w (3)
    // -----------------------------------------
    $display("\n--- LOAD WEIGHT #2 (non-SIMD) ---");
    in_w = 4'd5;
    inst_w[1:0] = 2'b01;
    // #10 inst_w[1:0] = 0;

    #10;
    $display("inst_e = %b (expected 001)", inst_e);
    $display("out_e  = %0d (expected 3)");


    // -----------------------------------------
    // 3) EXECUTE (inst = 010)
    // out_s = weight * in_w + in_n
    // weight = previously loaded = 5
    // -----------------------------------------
    $display("\n--- EXECUTE ---");
    in_w        = 4'd2;  // activation
    in_n        = 16'd10;  // psum input
    inst_w[1:0] = 2'b10;
    // #10 inst_w[1:0] = 0;

    #10;
    $display("out_s = %0d (expected 3*2 + 10 = 16)");

    $display("\n--- EXECUTE ---");
    in_w        = 4'd3;  // activation
    in_n        = 16'd5;  // psum input
    inst_w[1:0] = 2'b10;
    // #10 inst_w = 0;

    #10;

    $display("\n--- TEST COMPLETE ---");

    /// OS
    $display("\n Output stationary");
    reset  = 1;
    in_n   = 0;
    in_w   = 0;
    inst_w = 0;

    #20 reset = 0;
    inst_w[2] = 1;
    // execute, w = 2, a = 4, psum 8
    inst_w[1] = 1;
    in_n = 2;
    in_w = 4;

    #10
    // execute w = 4, a = 1, psum = 12, out_s = 2
    in_n = 4;
    in_w = 1;

    #10
    //execute w = -2, a = 1, psum = 10, out_s = 4
    in_n = 5'b01110;
    in_w = 1;

    #10
    //execute with 0 weight
    in_n = 0;

    #10
    //execute with 0 weight
    in_n = 0;

    #10
    // Wait
    inst_w[1] = 0;  // empty

    //wait
    #10
    //wait
    #10
    //wait
    #10

    #10
    //flush, in_n 511, out_s = 8
    // inst_w[1] = 0;
    inst_w[0] = 1;
    in_n = 0;

    #10
    // flush out_s = 511, in_n = -200
    in_n = 0;

    #20; #20; #20; #20;
    $finish;
  end

endmodule

Part2_SIMD/hardware/mac_tile_tb.vcd
$date
	Sat Nov 29 16:44:01 2025
$end
$version
	Icarus Verilog
$end
$timescale
	1ps
$end
$scope module mac_tile_tb $end
$var wire 16 ! out_s [15:0] $end
$var wire 4 " out_e [3:0] $end
$var wire 3 # inst_e [2:0] $end
$var reg 1 $ clk $end
$var reg 16 % in_n [15:0] $end
$var reg 4 & in_w [3:0] $end
$var reg 3 ' inst_w [2:0] $end
$var reg 1 ( reset $end
$scope module dut $end
$var wire 1 $ clk $end
$var wire 16 ) in_n [15:0] $end
$var wire 4 * in_w [3:0] $end
$var wire 3 + inst_e [2:0] $end
$var wire 3 , inst_w [2:0] $end
$var wire 4 - out_e [3:0] $end
$var wire 16 . out_s [15:0] $end
$var wire 1 ( reset $end
$var wire 16 / mac_out [15:0] $end
$var reg 4 0 a_q [3:0] $end
$var reg 4 1 b0_q [3:0] $end
$var reg 4 2 b1_q [3:0] $end
$var reg 16 3 c_q [15:0] $end
$var reg 3 4 inst_q [2:0] $end
$var reg 1 5 load_ready_q0 $end
$var reg 1 6 load_ready_q1 $end
$var reg 1 7 simd $end
$scope module mac_instance $end
$var wire 4 8 a [3:0] $end
$var wire 4 9 b0 [3:0] $end
$var wire 4 : b1 [3:0] $end
$var wire 16 ; c [15:0] $end
$var wire 1 7 simd $end
$var wire 16 < simd_psum [15:0] $end
$var wire 8 = shifted_product1 [7:0] $end
$var wire 16 > psum [15:0] $end
$var wire 6 ? product1 [5:0] $end
$var wire 6 @ product0 [5:0] $end
$var wire 16 A product [15:0] $end
$var wire 16 B out [15:0] $end
$var wire 3 C a_pad1 [2:0] $end
$var wire 3 D a_pad0 [2:0] $end
$upscope $end
$upscope $end
$upscope $end
$enddefinitions $end
#0
$dumpvars
b0xx D
b0xx C
bx B
bx A
bx @
bx ?
bx >
bx00 =
bx <
bx ;
bx :
bx 9
bx 8
x7
x6
x5
bx 4
bx 3
bx 2
bx 1
bx 0
bx /
bx .
bx -
b0 ,
bx +
b0 *
b0 )
1(
b0 '
b0 &
b0 %
0$
bx #
bx "
bx !
$end
#5000
b0 !
b0 .
b0 /
b0 B
b0 <
b0 >
b0 A
b0 @
b0 D
b0 =
b0 ?
b0 C
07
16
15
b0 #
b0 +
b0 4
b0 3
b0 ;
b0 2
b0 :
b0 1
b0 9
b0 "
b0 -
b0 0
b0 8
1$
#10000
0$
#15000
1$
#20000
0$
b1 '
b1 ,
b11 &
b11 *
0(
#25000
b1001 !
b1001 .
b1001 /
b1001 B
b1001 <
b1001 >
b1001 A
b1001 @
b11 D
06
05
b11 2
b11 :
b11 1
b11 9
b11 "
b11 -
b11 0
b11 8
1$
#30000
0$
b101 &
b101 *
#35000
b1111 !
b1111 .
b1111 /
b1111 B
b11 @
b1 D
b110 <
b1111 >
b1111 A
b1100 =
b11 ?
b1 C
b1 #
b1 +
b1 4
b101 "
b101 -
b101 0
b101 8
1$
#40000
0$
b10 '
b10 ,
b1010 %
b1010 )
b10 &
b10 *
#45000
b10000 !
b10000 .
b10000 /
b10000 B
b110 @
b10 D
b110 A
b0 =
b0 ?
b0 C
b10000 <
b10000 >
b1010 3
b1010 ;
b10 "
b10 -
b10 0
b10 8
b10 #
b10 +
b10 4
1$
#50000
0$
b0 '
b0 ,
b0 %
b0 )
b0 &
b0 *
1(
#55000
b0 !
b0 .
b0 /
b0 B
b0 D
16
15
b0 #
b0 +
b0 4
b0 3
b0 ;
b0 2
b0 :
b0 <
b0 >
b0 A
b0 @
b0 1
b0 9
b0 "
b0 -
b0 0
b0 8
1$
#60000
0$
#65000
1$
#70000
0$
b101 '
b101 ,
b10 &
b10 *
0(
#75000
b100 !
b100 .
b100 /
b100 B
b100 <
b100 >
b100 A
b100 @
b10 D
05
17
b10 1
b10 9
b10 "
b10 -
b10 0
b10 8
1$
#80000
0$
b100 &
b100 *
#85000
b0 @
b0 D
b100 <
b10000 >
b10000 A
b10000 =
b100 ?
b1 C
06
b100 2
b100 :
b100 "
b100 -
b100 0
b100 8
1$
#90000
0$
b101 &
b101 *
#95000
b110 !
b110 .
b110 /
b110 B
b110 <
b10010 >
b10010 A
b10 @
b1 D
b101 #
b101 +
b101 4
b101 "
b101 -
b101 0
b101 8
1$
#100000
0$
b110 &
b110 *
#105000
b1000 !
b1000 .
b1000 /
b1000 B
b1000 <
b10100 >
b10100 A
b100 @
b10 D
b110 "
b110 -
b110 0
b110 8
1$
#110000
0$
b111 &
b111 *
#115000
b1010 !
b1010 .
b1010 /
b1010 B
b1010 <
b10110 >
b10110 A
b110 @
b11 D
b111 "
b111 -
b111 0
b111 8
1$
#120000
0$
b100101100 %
b100101100 )
b10 '
b10 ,
b101 &
b101 *
#125000
b100110010 !
b100110010 .
b100110010 /
b100110010 B
b10010 A
b10 @
b1 D
b100110010 <
b100111110 >
b100101100 3
b100101100 ;
b101 "
b101 -
b101 0
b101 8
b10 #
b10 +
b10 4
1$
#130000
0$
b1111111011010100 %
b1111111011010100 )
b1010 &
b1010 *
#135000
b1111111011100000 !
b1111111011100000 .
b1111111011100000 /
b1111111011100000 B
b100 @
b10 D
b100100 A
b100000 =
b1000 ?
b10 C
b1111111011100000 <
b1111111011111000 >
b1111111011010100 3
b1111111011010100 ;
b1010 "
b1010 -
b1010 0
b1010 8
1$
