baseline/verilog/sram.v
// Created by prof. Mingu Kang @VVIP Lab in UCSD ECE department
// Please do not spread this code without permission 
module sram #(
    parameter depth = 2048,
    parameter DATA_W = 16,
    parameter ADDR_W = $clog2(depth)
)(CLK, D, Q, CEN, WEN, A);

  input  CLK;
  input  WEN;
  input  CEN;
  input  [DATA_W-1:0] D;
  input  [ADDR_W-1:0] A;
  output [DATA_W-1:0] Q;
  

  reg [DATA_W-1:0] memory [depth-1:0];
  reg [ADDR_W-1:0] add_q;
  assign Q = memory[add_q];

  always @ (posedge CLK) begin

   if (!CEN && WEN) // read 
      add_q <= A;
   if (!CEN && !WEN) // write
      memory[A] <= D; 

  end

endmodule

baseline/verilog/core.v
module core #(
    parameter bw  = 4,       // bit-width of activations
    parameter col = 8,       // PE columns
    parameter row = 8,       // PE rows
    parameter psum_bw = 16,  // Partial sum bit-width 
    parameter ADDR_W = 11   // SRAM Address width
)(
    input                          clk,
    input                          reset,
    input [33:0]                   inst,           // 34-bit instruction packet from testbench
    input [bw*row-1:0]             D_xmem,         // Data written to x-mem by testbench
    output                         ofifo_valid,    // Write enable for FIFO output
    output [col*psum_bw-1:0]       sfp_out    // Output feature map
);

    wire acc;
    wire CEN_pmem;
    wire WEN_pmem;
    wire CEN_xmem;
    wire WEN_xmem;
    wire ofifo_rd;
    wire ififo_wr;
    wire ififo_rd;
    wire l0_rd;
    wire l0_wr;
    wire execute;
    wire load;

    wire [10:0] A_pmem;   // bits [30:20]
    wire [10:0] A_xmem;   // bits [17:7]

    assign acc       = inst[33];
    assign CEN_pmem  = inst[32];
    assign WEN_pmem  = inst[31];
    assign A_pmem    = inst[30:20];
    assign CEN_xmem  = inst[19];
    assign WEN_xmem  = inst[18];
    assign A_xmem    = inst[17:7];
    assign ofifo_rd  = inst[6];
    assign ififo_wr  = inst[5];
    assign ififo_rd  = inst[4];
    assign l0_rd     = inst[3];
    assign l0_wr     = inst[2];
    assign execute   = inst[1];
    assign load      = inst[0];

    wire [bw*row-1:0] Q_wt;

    sram #(
        .ADDR_W  (ADDR_W),
        .DATA_W (bw*row)   
    ) activation_sram (
        .CLK (clk),
        .CEN (CEN_xmem),
        .WEN (WEN_xmem),
        .A   (A_xmem),
        .D   (D_xmem),
        .Q   (Q_wt)
    );

endmodule

baseline/verilog/core_tb.v
// Created by prof. Mingu Kang @VVIP Lab in UCSD ECE department
// Please do not spread this code without permission 
`timescale 1ns/1ps

module core_tb;

parameter bw = 4;
parameter psum_bw = 16;
parameter len_kij = 9;
parameter len_onij = 16;
parameter col = 8;
parameter row = 8;
parameter len_nij = 36;

reg clk = 0;
reg reset = 1;

wire [33:0] inst_q; 

reg [1:0]  inst_w_q = 0; 
reg [bw*row-1:0] D_xmem_q = 0;
reg CEN_xmem = 1;
reg WEN_xmem = 1;
reg [10:0] A_xmem = 0;
reg CEN_xmem_q = 1;
reg WEN_xmem_q = 1;
reg [10:0] A_xmem_q = 0;
reg CEN_pmem = 1;
reg WEN_pmem = 1;
reg [10:0] A_pmem = 0;
reg CEN_pmem_q = 1;
reg WEN_pmem_q = 1;
reg [10:0] A_pmem_q = 0;
reg ofifo_rd_q = 0;
reg ififo_wr_q = 0;
reg ififo_rd_q = 0;
reg l0_rd_q = 0;
reg l0_wr_q = 0;
reg execute_q = 0;
reg load_q = 0;
reg acc_q = 0;
reg acc = 0;

reg [1:0]  inst_w; 
reg [bw*row-1:0] D_xmem;
reg [psum_bw*col-1:0] answer;


reg ofifo_rd;
reg ififo_wr;
reg ififo_rd;
reg l0_rd;
reg l0_wr;
reg execute;
reg load;
reg [8*30:1] stringvar;
reg [8*64:1] w_file_name;
wire ofifo_valid;
wire [col*psum_bw-1:0] sfp_out;

integer x_file, x_scan_file ; // file_handler
integer w_file, w_scan_file ; // file_handler
integer acc_file, acc_scan_file ; // file_handler
integer out_file, out_scan_file ; // file_handler
integer captured_data; 
integer t, i, j, k, kij;
integer error;

assign inst_q[33] = acc_q;
assign inst_q[32] = CEN_pmem_q;
assign inst_q[31] = WEN_pmem_q;
assign inst_q[30:20] = A_pmem_q;
assign inst_q[19]   = CEN_xmem_q;
assign inst_q[18]   = WEN_xmem_q;
assign inst_q[17:7] = A_xmem_q;
assign inst_q[6]   = ofifo_rd_q;
assign inst_q[5]   = ififo_wr_q;
assign inst_q[4]   = ififo_rd_q;
assign inst_q[3]   = l0_rd_q;
assign inst_q[2]   = l0_wr_q;
assign inst_q[1]   = execute_q; 
assign inst_q[0]   = load_q; 


core  #(.bw(bw), .col(col), .row(row)) core_instance (
	.clk(clk), 
  .reset(reset),
	.inst(inst_q),
	.ofifo_valid(ofifo_valid),
  .D_xmem(D_xmem_q), 
  .sfp_out(sfp_out)
	); 

initial begin 

  inst_w   = 0; 
  D_xmem   = 0;
  CEN_xmem = 1;
  WEN_xmem = 1;
  A_xmem   = 0;
  ofifo_rd = 0;
  ififo_wr = 0;
  ififo_rd = 0;
  l0_rd    = 0;
  l0_wr    = 0;
  execute  = 0;
  load     = 0;

  $dumpfile("core_tb.vcd");
  $dumpvars(0,core_tb);

  x_file = $fopen("./verilog/activation_tile0.txt", "r");
  // Following three lines are to remove the first three comment lines of the file
  x_scan_file = $fscanf(x_file,"%s", captured_data);
  x_scan_file = $fscanf(x_file,"%s", captured_data);
  x_scan_file = $fscanf(x_file,"%s", captured_data);

  //////// Reset /////////
  #0.5 clk = 1'b0;   reset = 1;
  #0.5 clk = 1'b1; 

  for (i=0; i<10 ; i=i+1) begin
    #0.5 clk = 1'b0;
    #0.5 clk = 1'b1;  
  end

  #0.5 clk = 1'b0;   reset = 0;
  #0.5 clk = 1'b1; 

  #0.5 clk = 1'b0;   
  #0.5 clk = 1'b1;   
  /////////////////////////

  /////// Activation data writing to memory ///////
  for (t=0; t<len_nij; t=t+1) begin  
    #0.5 clk = 1'b0;  x_scan_file = $fscanf(x_file,"%32b", D_xmem); WEN_xmem = 0; CEN_xmem = 0; if (t>0) A_xmem = A_xmem + 1;
    #0.5 clk = 1'b1;   
  end

  #0.5 clk = 1'b0;  WEN_xmem = 1;  CEN_xmem = 1; A_xmem = 0;
  #0.5 clk = 1'b1; 

  $fclose(x_file);
  /////////////////////////////////////////////////

  for (kij=0; kij<9; kij=kij+1) begin  // kij loop

    case(kij)
     0: w_file_name = "./verilog/weight_itile0_otile0_kij0.txt";
     1: w_file_name = "./verilog/weight_itile0_otile0_kij1.txt";
     2: w_file_name = "./verilog/weight_itile0_otile0_kij2.txt";
     3: w_file_name = "./verilog/weight_itile0_otile0_kij3.txt";
     4: w_file_name = "./verilog/weight_itile0_otile0_kij4.txt";
     5: w_file_name = "./verilog/weight_itile0_otile0_kij5.txt";
     6: w_file_name = "./verilog/weight_itile0_otile0_kij6.txt";
     7: w_file_name = "./verilog/weight_itile0_otile0_kij7.txt";
     8: w_file_name = "./verilog/weight_itile0_otile0_kij8.txt";
    endcase
    
    w_file = $fopen(w_file_name, "r");
    // Following three lines are to remove the first three comment lines of the file
    w_scan_file = $fscanf(w_file,"%s", captured_data);
    w_scan_file = $fscanf(w_file,"%s", captured_data);
    w_scan_file = $fscanf(w_file,"%s", captured_data);

    #0.5 clk = 1'b0;   reset = 1;
    #0.5 clk = 1'b1; 

    for (i=0; i<10 ; i=i+1) begin
      #0.5 clk = 1'b0;
      #0.5 clk = 1'b1;  
    end

    #0.5 clk = 1'b0;   reset = 0;
    #0.5 clk = 1'b1; 

    #0.5 clk = 1'b0;   
    #0.5 clk = 1'b1;   





    /////// Kernel data writing to memory ///////

    A_xmem = 11'b10000000000;

    for (t=0; t<col; t=t+1) begin  
      #0.5 clk = 1'b0;  w_scan_file = $fscanf(w_file,"%32b", D_xmem); WEN_xmem = 0; CEN_xmem = 0; if (t>0) A_xmem = A_xmem + 1; 
      #0.5 clk = 1'b1;  
    end

    #0.5 clk = 1'b0;  WEN_xmem = 1;  CEN_xmem = 1; A_xmem = 0;
    #0.5 clk = 1'b1; 
    /////////////////////////////////////



    /////// Kernel data writing to L0 ///////
    //...
    /////////////////////////////////////



    /////// Kernel loading to PEs ///////
    //...
    /////////////////////////////////////
  


    ////// provide some intermission to clear up the kernel loading ///
    #0.5 clk = 1'b0;  load = 0; l0_rd = 0;
    #0.5 clk = 1'b1;  
  

    for (i=0; i<10 ; i=i+1) begin
      #0.5 clk = 1'b0;
      #0.5 clk = 1'b1;  
    end
    /////////////////////////////////////



    /////// Activation data writing to L0 ///////
    //...
    /////////////////////////////////////



    /////// Execution ///////
    //...
    /////////////////////////////////////



    //////// OFIFO READ ////////
    // Ideally, OFIFO should be read while execution, but we have enough ofifo
    // depth so we can fetch out after execution.
    //...
    /////////////////////////////////////


  end  // end of kij loop


  ////////// Accumulation /////////
  out_file = $fopen("./verilog/out.txt", "r");  

  // Following three lines are to remove the first three comment lines of the file
  out_scan_file = $fscanf(out_file,"%s", answer); 
  out_scan_file = $fscanf(out_file,"%s", answer); 
  out_scan_file = $fscanf(out_file,"%s", answer); 

  error = 0;



  $display("############ Verification Start during accumulation #############"); 

  for (i=0; i<len_onij+1; i=i+1) begin 

    #0.5 clk = 1'b0; 
    #0.5 clk = 1'b1; 

    if (i>0) begin
     out_scan_file = $fscanf(out_file,"%128b", answer); // reading from out file to answer
       if (sfp_out == answer)
         $display("%2d-th output featuremap Data matched! :D", i); 
       else begin
         $display("%2d-th output featuremap Data ERROR!!", i); 
         $display("sfpout: %128b", sfp_out);
         $display("answer: %128b", answer);
         error = 1;
       end
    end
   
 
    #0.5 clk = 1'b0; reset = 1;
    #0.5 clk = 1'b1;  
    #0.5 clk = 1'b0; reset = 0; 
    #0.5 clk = 1'b1;  

    for (j=0; j<len_kij+1; j=j+1) begin 

      #0.5 clk = 1'b0;   
        if (j<len_kij) begin CEN_pmem = 0; WEN_pmem = 1; acc_scan_file = $fscanf(acc_file,"%11b", A_pmem); end
                       else  begin CEN_pmem = 1; WEN_pmem = 1; end

        if (j>0)  acc = 1;  
      #0.5 clk = 1'b1;   
    end

    #0.5 clk = 1'b0; acc = 0;
    #0.5 clk = 1'b1; 
  end


  if (error == 0) begin
  	$display("############ No error detected ##############"); 
  	$display("########### Project Completed !! ############"); 

  end

  $fclose(acc_file);
  //////////////////////////////////

  for (t=0; t<10; t=t+1) begin  
    #0.5 clk = 1'b0;  
    #0.5 clk = 1'b1;  
  end

  #10 $finish;

end

always @ (posedge clk) begin
   inst_w_q   <= inst_w; 
   D_xmem_q   <= D_xmem;
   CEN_xmem_q <= CEN_xmem;
   WEN_xmem_q <= WEN_xmem;
   A_pmem_q   <= A_pmem;
   CEN_pmem_q <= CEN_pmem;
   WEN_pmem_q <= WEN_pmem;
   A_xmem_q   <= A_xmem;
   ofifo_rd_q <= ofifo_rd;
   acc_q      <= acc;
   ififo_wr_q <= ififo_wr;
   ififo_rd_q <= ififo_rd;
   l0_rd_q    <= l0_rd;
   l0_wr_q    <= l0_wr ;
   execute_q  <= execute;
   load_q     <= load;
end


endmodule

baseline/core_tb.vcd
$date
	Mon Nov 24 02:42:03 2025
$end
$version
	Icarus Verilog
$end
$timescale
	1ps
$end
$scope module core_tb $end
$var wire 1 ! ofifo_valid $end
$var wire 128 " sfp_out [127:0] $end
$var wire 34 # inst_q [33:0] $end
$var reg 11 $ A_pmem [10:0] $end
$var reg 11 % A_pmem_q [10:0] $end
$var reg 11 & A_xmem [10:0] $end
$var reg 11 ' A_xmem_q [10:0] $end
$var reg 1 ( CEN_pmem $end
$var reg 1 ) CEN_pmem_q $end
$var reg 1 * CEN_xmem $end
$var reg 1 + CEN_xmem_q $end
$var reg 32 , D_xmem [31:0] $end
$var reg 32 - D_xmem_q [31:0] $end
$var reg 1 . WEN_pmem $end
$var reg 1 / WEN_pmem_q $end
$var reg 1 0 WEN_xmem $end
$var reg 1 1 WEN_xmem_q $end
$var reg 1 2 acc $end
$var reg 1 3 acc_q $end
$var reg 128 4 answer [127:0] $end
$var reg 1 5 clk $end
$var reg 1 6 execute $end
$var reg 1 7 execute_q $end
$var reg 1 8 ififo_rd $end
$var reg 1 9 ififo_rd_q $end
$var reg 1 : ififo_wr $end
$var reg 1 ; ififo_wr_q $end
$var reg 2 < inst_w [1:0] $end
$var reg 2 = inst_w_q [1:0] $end
$var reg 1 > l0_rd $end
$var reg 1 ? l0_rd_q $end
$var reg 1 @ l0_wr $end
$var reg 1 A l0_wr_q $end
$var reg 1 B load $end
$var reg 1 C load_q $end
$var reg 1 D ofifo_rd $end
$var reg 1 E ofifo_rd_q $end
$var reg 1 F reset $end
$var reg 512 G w_file_name [512:1] $end
$var integer 32 H acc_file [31:0] $end
$var integer 32 I acc_scan_file [31:0] $end
$var integer 32 J captured_data [31:0] $end
$var integer 32 K error [31:0] $end
$var integer 32 L i [31:0] $end
$var integer 32 M j [31:0] $end
$var integer 32 N kij [31:0] $end
$var integer 32 O out_file [31:0] $end
$var integer 32 P out_scan_file [31:0] $end
$var integer 32 Q t [31:0] $end
$var integer 32 R w_file [31:0] $end
$var integer 32 S w_scan_file [31:0] $end
$var integer 32 T x_file [31:0] $end
$var integer 32 U x_scan_file [31:0] $end
$scope module core_instance $end
$var wire 32 V D_xmem [31:0] $end
$var wire 1 5 clk $end
$var wire 34 W inst [33:0] $end
$var wire 1 ! ofifo_valid $end
$var wire 1 F reset $end
$var wire 128 X sfp_out [127:0] $end
$var wire 1 Y ofifo_rd $end
$var wire 1 Z load $end
$var wire 1 [ l0_wr $end
$var wire 1 \ l0_rd $end
$var wire 1 ] ififo_wr $end
$var wire 1 ^ ififo_rd $end
$var wire 1 _ execute $end
$var wire 1 ` acc $end
$var wire 1 a WEN_xmem $end
$var wire 1 b WEN_pmem $end
$var wire 32 c Q_wt [31:0] $end
$var wire 1 d CEN_xmem $end
$var wire 1 e CEN_pmem $end
$var wire 11 f A_xmem [10:0] $end
$var wire 11 g A_pmem [10:0] $end
$scope module activation_sram $end
$var wire 11 h A [10:0] $end
$var wire 1 d CEN $end
$var wire 1 5 CLK $end
$var wire 32 i D [31:0] $end
$var wire 32 j Q [31:0] $end
$var wire 1 a WEN $end
$var reg 11 k add_q [10:0] $end
$upscope $end
$upscope $end
$upscope $end
$enddefinitions $end
#0
$dumpvars
bx k
bx j
b0 i
b0 h
b0 g
b0 f
1e
1d
bx c
1b
1a
0`
0_
0^
0]
0\
0[
0Z
0Y
bz X
b110000000000011000000000000000000 W
b0 V
b1 U
b10000000000000000000000000000011 T
bx S
bx R
bx Q
bx P
bx O
bx N
bx M
bx L
bx K
b101110001011100010111000100011 J
bx I
bx H
bx G
1F
0E
0D
0C
0B
0A
0@
0?
0>
b0 =
b0 <
0;
0:
09
08
07
06
05
bx 4
03
02
11
10
1/
1.
b0 -
b0 ,
1+
1*
1)
1(
b0 '
b0 &
b0 %
b0 $
b110000000000011000000000000000000 #
bz "
z!
$end
#1000
b0 L
15
#1500
05
#2000
b1 L
15
#2500
05
#3000
b10 L
15
#3500
05
#4000
b11 L
15
#4500
05
#5000
b100 L
15
#5500
05
#6000
b101 L
15
#6500
05
#7000
b110 L
15
#7500
05
#8000
b111 L
15
#8500
05
#9000
b1000 L
15
#9500
05
#10000
b1001 L
15
#10500
05
#11000
b1010 L
15
#11500
0F
05
#12000
15
#12500
05
#13000
b0 Q
15
#13500
0*
00
05
#14000
0a
0d
01
b110000000000000000000000000000000 #
b110000000000000000000000000000000 W
0+
b1 Q
15
#14500
b1 &
05
#15000
b1 f
b1 h
b110000000000000000000000010000000 #
b110000000000000000000000010000000 W
b1 '
b10 Q
15
#15500
b10 &
05
#16000
b10 f
b10 h
b110000000000000000000000100000000 #
b110000000000000000000000100000000 W
b10 '
b11 Q
15
#16500
b11 &
05
#17000
b11 f
b11 h
b110000000000000000000000110000000 #
b110000000000000000000000110000000 W
b11 '
b100 Q
15
#17500
b100 &
05
#18000
b100 f
b100 h
b110000000000000000000001000000000 #
b110000000000000000000001000000000 W
b100 '
b101 Q
15
#18500
b101 &
05
#19000
b101 f
b101 h
b110000000000000000000001010000000 #
b110000000000000000000001010000000 W
b101 '
b110 Q
15
#19500
b110 &
05
#20000
b110 f
b110 h
b110000000000000000000001100000000 #
b110000000000000000000001100000000 W
b110 '
b111 Q
15
#20500
b111 &
b11000000000000010010000000000000 ,
05
#21000
b111 f
b111 h
b110000000000000000000001110000000 #
b110000000000000000000001110000000 W
b111 '
b11000000000000010010000000000000 -
b11000000000000010010000000000000 V
b11000000000000010010000000000000 i
b1000 Q
15
#21500
b1000 &
b11110000000000000101000000000000 ,
05
#22000
b1000 f
b1000 h
b110000000000000000000010000000000 #
b110000000000000000000010000000000 W
b1000 '
b11110000000000000101000000000000 -
b11110000000000000101000000000000 V
b11110000000000000101000000000000 i
b1001 Q
15
#22500
b1001 &
b11110000000000001100000000000000 ,
05
#23000
b1001 f
b1001 h
b110000000000000000000010010000000 #
b110000000000000000000010010000000 W
b1001 '
b11110000000000001100000000000000 -
b11110000000000001100000000000000 V
b11110000000000001100000000000000 i
b1010 Q
15
#23500
b1010 &
b10010000000000001011000000000000 ,
05
#24000
b1010 f
b1010 h
b110000000000000000000010100000000 #
b110000000000000000000010100000000 W
b1010 '
b10010000000000001011000000000000 -
b10010000000000001011000000000000 V
b10010000000000001011000000000000 i
b1011 Q
15
#24500
b1011 &
b0 ,
05
#25000
b1011 f
b1011 h
b110000000000000000000010110000000 #
b110000000000000000000010110000000 W
b1011 '
b0 -
b0 V
b0 i
b1100 Q
15
#25500
b1100 &
05
#26000
b1100 f
b1100 h
b110000000000000000000011000000000 #
b110000000000000000000011000000000 W
b1100 '
b1101 Q
15
#26500
b1101 &
b11110000000000000000000000000000 ,
05
#27000
b1101 f
b1101 h
b110000000000000000000011010000000 #
b110000000000000000000011010000000 W
b1101 '
b11110000000000000000000000000000 -
b11110000000000000000000000000000 V
b11110000000000000000000000000000 i
b1110 Q
15
#27500
b1110 &
05
#28000
b1110 f
b1110 h
b110000000000000000000011100000000 #
b110000000000000000000011100000000 W
b1110 '
b1111 Q
15
#28500
b1111 &
b11110000000000000000000000010000 ,
05
#29000
b1111 f
b1111 h
b110000000000000000000011110000000 #
b110000000000000000000011110000000 W
b1111 '
b11110000000000000000000000010000 -
b11110000000000000000000000010000 V
b11110000000000000000000000010000 i
b10000 Q
15
#29500
b10000 &
b10000000000000010001000000000000 ,
05
#30000
b10000 f
b10000 h
b110000000000000000000100000000000 #
b110000000000000000000100000000000 W
b10000 '
b10000000000000010001000000000000 -
b10000000000000010001000000000000 V
b10000000000000010001000000000000 i
b10001 Q
15
#30500
b10001 &
b0 ,
05
#31000
b10001 f
b10001 h
b110000000000000000000100010000000 #
b110000000000000000000100010000000 W
b10001 '
b0 -
b0 V
b0 i
b10010 Q
15
#31500
b10010 &
05
#32000
b10010 f
b10010 h
b110000000000000000000100100000000 #
b110000000000000000000100100000000 W
b10010 '
b10011 Q
15
#32500
b10011 &
b1010000000000000000 ,
05
#33000
b10011 f
b10011 h
b110000000000000000000100110000000 #
b110000000000000000000100110000000 W
b10011 '
b1010000000000000000 -
b1010000000000000000 V
b1010000000000000000 i
b10100 Q
15
#33500
b10100 &
b1000000000000000000 ,
05
#34000
b10100 f
b10100 h
b110000000000000000000101000000000 #
b110000000000000000000101000000000 W
b10100 '
b1000000000000000000 -
b1000000000000000000 V
b1000000000000000000 i
b10101 Q
15
#34500
b10101 &
b10100000000000010000 ,
05
#35000
b10101 f
b10101 h
b110000000000000000000101010000000 #
b110000000000000000000101010000000 W
b10101 '
b10100000000000010000 -
b10100000000000010000 V
b10100000000000010000 i
b10110 Q
15
#35500
b10110 &
b11110000000000000000 ,
05
#36000
b10110 f
b10110 h
b110000000000000000000101100000000 #
b110000000000000000000101100000000 W
b10110 '
b11110000000000000000 -
b11110000000000000000 V
b11110000000000000000 i
b10111 Q
15
#36500
b10111 &
b0 ,
05
#37000
b10111 f
b10111 h
b110000000000000000000101110000000 #
b110000000000000000000101110000000 W
b10111 '
b0 -
b0 V
b0 i
b11000 Q
15
#37500
b11000 &
05
#38000
b11000 f
b11000 h
b110000000000000000000110000000000 #
b110000000000000000000110000000000 W
b11000 '
b11001 Q
15
#38500
b11001 &
b10100010000000000000 ,
05
#39000
b11001 f
b11001 h
b110000000000000000000110010000000 #
b110000000000000000000110010000000 W
b11001 '
b10100010000000000000 -
b10100010000000000000 V
b10100010000000000000 i
b11010 Q
15
#39500
b11010 &
b11110000000000000000 ,
05
#40000
b11010 f
b11010 h
b110000000000000000000110100000000 #
b110000000000000000000110100000000 W
b11010 '
b11110000000000000000 -
b11110000000000000000 V
b11110000000000000000 i
b11011 Q
15
#40500
b11011 &
05
#41000
b11011 f
b11011 h
b110000000000000000000110110000000 #
b110000000000000000000110110000000 W
b11011 '
b11100 Q
15
#41500
b11100 &
05
#42000
b11100 f
b11100 h
b110000000000000000000111000000000 #
b110000000000000000000111000000000 W
b11100 '
b11101 Q
15
#42500
b11101 &
b0 ,
05
#43000
b11101 f
b11101 h
b110000000000000000000111010000000 #
b110000000000000000000111010000000 W
b11101 '
b0 -
b0 V
b0 i
b11110 Q
15
#43500
b11110 &
05
#44000
b11110 f
b11110 h
b110000000000000000000111100000000 #
b110000000000000000000111100000000 W
b11110 '
b11111 Q
15
#44500
b11111 &
05
#45000
b11111 f
b11111 h
b110000000000000000000111110000000 #
b110000000000000000000111110000000 W
b11111 '
b100000 Q
15
#45500
b100000 &
05
#46000
b100000 f
b100000 h
b110000000000000000001000000000000 #
b110000000000000000001000000000000 W
b100000 '
b100001 Q
15
#46500
b100001 &
05
#47000
b100001 f
b100001 h
b110000000000000000001000010000000 #
b110000000000000000001000010000000 W
b100001 '
b100010 Q
15
#47500
b100010 &
05
#48000
b100010 f
b100010 h
b110000000000000000001000100000000 #
b110000000000000000001000100000000 W
b100010 '
b100011 Q
15
#48500
b100011 &
05
#49000
b100011 f
b100011 h
b110000000000000000001000110000000 #
b110000000000000000001000110000000 W
b100011 '
b100100 Q
15
#49500
b0 &
1*
10
05
#50000
b0 f
b0 h
1a
1d
b0 '
11
b110000000000011000000000000000000 #
b110000000000011000000000000000000 W
1+
b1 S
b101110001011100010111000100011 J
b10000000000000000000000000000011 R
b1011100010111101110110011001010111001001101001011011000110111101100111001011110111011101100101011010010110011101101000011101000101111101101001011101000110100101101100011001010011000001011111011011110111010001101001011011000110010100110000010111110110101101101001011010100011000000101110011101000111100001110100 G
b0 N
15
#50500
1F
05
#51000
b0 L
15
#51500
05
#52000
b1 L
15
#52500
05
#53000
b10 L
15
#53500
05
#54000
b11 L
15
#54500
05
#55000
b100 L
15
#55500
05
#56000
b101 L
15
#56500
05
#57000
b110 L
15
#57500
05
#58000
b111 L
15
#58500
05
#59000
b1000 L
15
#59500
05
#60000
b1001 L
15
#60500
05
#61000
b1010 L
15
#61500
0F
05
#62000
15
#62500
05
#63000
b10000000000 f
b10000000000 h
b110000000000011100000000000000000 #
b110000000000011100000000000000000 W
b10000000000 '
b0 Q
b10000000000 &
15
#63500
0*
00
b1110000110110011001011111100100 ,
05
#64000
0a
0d
01
b110000000000000100000000000000000 #
b110000000000000100000000000000000 W
0+
b1110000110110011001011111100100 -
b1110000110110011001011111100100 V
b1110000110110011001011111100100 i
b1 Q
15
#64500
b10000000001 &
b11011011101110011001100101010001 ,
05
#65000
b10000000001 f
b10000000001 h
b110000000000000100000000010000000 #
b110000000000000100000000010000000 W
b10000000001 '
b11011011101110011001100101010001 -
b11011011101110011001100101010001 V
b11011011101110011001100101010001 i
b10 Q
15
#65500
b10000000010 &
b1110101011110011001011101110100 ,
05
#66000
b10000000010 f
b10000000010 h
b110000000000000100000000100000000 #
b110000000000000100000000100000000 W
b10000000010 '
b1110101011110011001011101110100 -
b1110101011110011001011101110100 V
b1110101011110011001011101110100 i
b11 Q
15
#66500
b10000000011 &
b10010111011101111001011111111111 ,
05
#67000
b10000000011 f
b10000000011 h
b110000000000000100000000110000000 #
b110000000000000100000000110000000 W
b10000000011 '
b10010111011101111001011111111111 -
b10010111011101111001011111111111 V
b10010111011101111001011111111111 i
b100 Q
15
#67500
b10000000100 &
b10011001000010011001011110011101 ,
05
#68000
b10000000100 f
b10000000100 h
b110000000000000100000001000000000 #
b110000000000000100000001000000000 W
b10000000100 '
b10011001000010011001011110011101 -
b10011001000010011001011110011101 V
b10011001000010011001011110011101 i
b101 Q
15
#68500
b10000000101 &
b1111011111010011001011100001001 ,
05
#69000
b10000000101 f
b10000000101 h
b110000000000000100000001010000000 #
b110000000000000100000001010000000 W
b10000000101 '
b1111011111010011001011100001001 -
b1111011111010011001011100001001 V
b1111011111010011001011100001001 i
b110 Q
15
#69500
b10000000110 &
b1110110011101110111011110011111 ,
05
#70000
b10000000110 f
b10000000110 h
b110000000000000100000001100000000 #
b110000000000000100000001100000000 W
b10000000110 '
b1110110011101110111011110011111 -
b1110110011101110111011110011111 V
b1110110011101110111011110011111 i
b111 Q
15
#70500
b10000000111 &
b1110100010001111001011110010101 ,
05
#71000
b10000000111 f
b10000000111 h
b110000000000000100000001110000000 #
b110000000000000100000001110000000 W
b10000000111 '
b1110100010001111001011110010101 -
b1110100010001111001011110010101 V
b1110100010001111001011110010101 i
b1000 Q
15
#71500
b0 &
1*
10
05
#72000
b0 f
b0 h
1a
1d
b0 '
11
b110000000000011000000000000000000 #
b110000000000011000000000000000000 W
1+
15
#72500
05
#73000
b0 L
15
#73500
05
#74000
b1 L
15
#74500
05
#75000
b10 L
15
#75500
05
#76000
b11 L
15
#76500
05
#77000
b100 L
15
#77500
05
#78000
b101 L
15
#78500
05
#79000
b110 L
15
#79500
05
#80000
b111 L
15
#80500
05
#81000
b1000 L
15
#81500
05
#82000
b1001 L
15
#82500
05
#83000
b101110001011100010111000100011 J
b10000000000000000000000000000100 R
b1011100010111101110110011001010111001001101001011011000110111101100111001011110111011101100101011010010110011101101000011101000101111101101001011101000110100101101100011001010011000001011111011011110111010001101001011011000110010100110000010111110110101101101001011010100011000100101110011101000111100001110100 G
b1 N
b1010 L
15
#83500
1F
05
#84000
b0 L
15
#84500
05
#85000
b1 L
15
#85500
05
#86000
b10 L
15
#86500
05
#87000
b11 L
15
#87500
05
#88000
b100 L
15
#88500
05
#89000
b101 L
15
#89500
05
#90000
b110 L
15
#90500
05
#91000
b111 L
15
#91500
05
#92000
b1000 L
15
#92500
05
#93000
b1001 L
15
#93500
05
#94000
b1010 L
15
#94500
0F
05
#95000
15
#95500
05
#96000
b10000000000 f
b10000000000 h
b110000000000011100000000000000000 #
b110000000000011100000000000000000 W
b10000000000 '
b0 Q
b10000000000 &
15
#96500
0*
00
b1111001110010011001011110101111 ,
05
#97000
0a
0d
01
b110000000000000100000000000000000 #
b110000000000000100000000000000000 W
0+
b1111001110010011001011110101111 -
b1111001110010011001011110101111 V
b1111001110010011001011110101111 i
b1 Q
15
#97500
b10000000001 &
b11111001100110011001000111001001 ,
05
#98000
b10000000001 f
b10000000001 h
b110000000000000100000000010000000 #
b110000000000000100000000010000000 W
b10000000001 '
b11111001100110011001000111001001 -
b11111001100110011001000111001001 V
b11111001100110011001000111001001 i
b10 Q
15
#98500
b10000000010 &
b10010111011101111001011101111111 ,
05
#99000
b10000000010 f
b10000000010 h
b110000000000000100000000100000000 #
b110000000000000100000000100000000 W
b10000000010 '
b10010111011101111001011101111111 -
b10010111011101111001011101111111 V
b10010111011101111001011101111111 i
b11 Q
15
#99500
b10000000011 &
b10010011111010011001011110010101 ,
05
#100000
b10000000011 f
b10000000011 h
b110000000000000100000000110000000 #
b110000000000000100000000110000000 W
b10000000011 '
b10010011111010011001011110010101 -
b10010011111010011001011110010101 V
b10010011111010011001011110010101 i
b100 Q
15
#100500
b10000000100 &
b10011001000010010111100110011001 ,
05
#101000
b10000000100 f
b10000000100 h
b110000000000000100000001000000000 #
b110000000000000100000001000000000 W
b10000000100 '
b10011001000010010111100110011001 -
b10011001000010010111100110011001 V
b10011001000010010111100110011001 i
b101 Q
15
#101500
b10000000101 &
b10011001100110011001100111111001 ,
05
#102000
b10000000101 f
b10000000101 h
b110000000000000100000001010000000 #
b110000000000000100000001010000000 W
b10000000101 '
b10011001100110011001100111111001 -
b10011001100110011001100111111001 V
b10011001100110011001100111111001 i
b110 Q
15
#102500
b10000000110 &
b10010110011110011001011110010100 ,
05
#103000
b10000000110 f
b10000000110 h
b110000000000000100000001100000000 #
b110000000000000100000001100000000 W
b10000000110 '
b10010110011110011001011110010100 -
b10010110011110011001011110010100 V
b10010110011110011001011110010100 i
b111 Q
15
#103500
b10000000111 &
b1111101000001111001011110010000 ,
05
#104000
b10000000111 f
b10000000111 h
b110000000000000100000001110000000 #
b110000000000000100000001110000000 W
b10000000111 '
b1111101000001111001011110010000 -
b1111101000001111001011110010000 V
b1111101000001111001011110010000 i
b1000 Q
15
#104500
b0 &
1*
10
05
#105000
b0 f
b0 h
1a
1d
b0 '
11
b110000000000011000000000000000000 #
b110000000000011000000000000000000 W
1+
15
#105500
05
#106000
b0 L
15
#106500
05
#107000
b1 L
15
#107500
05
#108000
b10 L
15
#108500
05
#109000
b11 L
15
#109500
05
#110000
b100 L
15
#110500
05
#111000
b101 L
15
#111500
05
#112000
b110 L
15
#112500
05
#113000
b111 L
15
#113500
05
#114000
b1000 L
15
#114500
05
#115000
b1001 L
15
#115500
05
#116000
b101110001011100010111000100011 J
b10000000000000000000000000000101 R
b1011100010111101110110011001010111001001101001011011000110111101100111001011110111011101100101011010010110011101101000011101000101111101101001011101000110100101101100011001010011000001011111011011110111010001101001011011000110010100110000010111110110101101101001011010100011001000101110011101000111100001110100 G
b10 N
b1010 L
15
#116500
1F
05
#117000
b0 L
15
#117500
05
#118000
b1 L
15
#118500
05
#119000
b10 L
15
#119500
05
#120000
b11 L
15
#120500
05
#121000
b100 L
15
#121500
05
